mission/__init__.py
mission/app.py
mission/phase1.py
mission/phase2.py
mission/session.py
polyrents_challenge-0.1.0.dist-info/DESCRIPTION.rst
polyrents_challenge-0.1.0.dist-info/METADATA
polyrents_challenge-0.1.0.dist-info/RECORD
polyrents_challenge-0.1.0.dist-info/WHEEL
polyrents_challenge-0.1.0.dist-info/metadata.json
polyrents_challenge-0.1.0.dist-info/top_level.txt
